specify_cli/__init__.py
specify_cli-0.0.22.dist-info/METADATA
specify_cli-0.0.22.dist-info/WHEEL
specify_cli-0.0.22.dist-info/entry_points.txt
specify_cli-0.0.22.dist-info/licenses/LICENSE
specify_cli-0.0.22.dist-info/RECORD
