Metadata-Version: 2.4
Name: specify-cli
Version: 0.0.22
Summary: Specify CLI, part of GitHub Spec Kit. A tool to bootstrap your projects for Spec-Driven Development (SDD).
License-File: LICENSE
Requires-Python: >=3.11
Requires-Dist: httpx[socks]
Requires-Dist: platformdirs
Requires-Dist: readchar
Requires-Dist: rich
Requires-Dist: truststore>=0.10.4
Requires-Dist: typer
